tarakimu/__init__.py
tarakimu/utils.py
tarakimu-0.2.0.dist-info/DESCRIPTION.rst
tarakimu-0.2.0.dist-info/METADATA
tarakimu-0.2.0.dist-info/RECORD
tarakimu-0.2.0.dist-info/WHEEL
tarakimu-0.2.0.dist-info/entry_points.txt
tarakimu-0.2.0.dist-info/metadata.json
tarakimu-0.2.0.dist-info/top_level.txt
