Metadata-Version: 2.0
Name: tarakimu
Version: 0.2.0
Summary: A python library for number to Swahili words conversion
Home-page: https://github.com/tehamalab/tarakimu
Author: Tehamalab
Author-email: developers@tehamalab.com
License: BSD license
Keywords: tarakimu
Platform: UNKNOWN
Classifier: Development Status :: 2 - Pre-Alpha
Classifier: Intended Audience :: Developers
Classifier: License :: OSI Approved :: BSD License
Classifier: Natural Language :: English
Classifier: Programming Language :: Python :: 2
Classifier: Programming Language :: Python :: 2.7
Classifier: Programming Language :: Python :: 3
Classifier: Programming Language :: Python :: 3.4
Classifier: Programming Language :: Python :: 3.5
Classifier: Programming Language :: Python :: 3.6
Requires-Dist: Click (>=6.0)
